python_bayeux/__init__.py
python_bayeux-1.0.0.dist-info/LICENSE
python_bayeux-1.0.0.dist-info/METADATA
python_bayeux-1.0.0.dist-info/WHEEL
python_bayeux-1.0.0.dist-info/top_level.txt
python_bayeux-1.0.0.dist-info/RECORD
