Metadata-Version: 2.1
Name: python-bayeux
Version: 1.0.0
Summary: A bayeux client for python.
Home-page: https://github.com/SalesforceFoundation/python-bayeux
Author: Adam J. Lincoln
Author-email: alincoln@salesforce.com
License: BSD 3-Clause
Download-URL: https://github.com/SalesforceFoundation/python-bayeux/tarball/1.0.0
Keywords: bayeux cometd
Platform: UNKNOWN
Requires-Dist: requests
Requires-Dist: gevent
Requires-Dist: simplejson
